anchor/__init__.py
anchor/cooccur.py
anchor/projection.py
anchor/recover.py
anchor/search.py
anchor/topics.py
anchor_topic/__init__.py
anchor_topic/cooccur.py
anchor_topic/projection.py
anchor_topic/recover.py
anchor_topic/search.py
anchor_topic/topics.py
anchor_topic-0.1.1.dist-info/DESCRIPTION.rst
anchor_topic-0.1.1.dist-info/METADATA
anchor_topic-0.1.1.dist-info/RECORD
anchor_topic-0.1.1.dist-info/WHEEL
anchor_topic-0.1.1.dist-info/metadata.json
anchor_topic-0.1.1.dist-info/top_level.txt
