Metadata-Version: 2.0
Name: anchor-topic
Version: 0.1.1
Summary: A package for anchor-based topic models.
Home-page: https://github.com/forest-snow/anchor-topic
Author: Michelle Yuan
Author-email: myuan@cs.umd.edu
License: MIT License
Requires-Dist: numba
Requires-Dist: numpy
Requires-Dist: scipy
